<?xml version="1.0" encoding="UTF-8"?>
<!DOCTYPE mapper PUBLIC "-//mybatis.org//DTD Mapper 3.0//EN" "http://mybatis.org/dtd/mybatis-3-mapper.dtd">

<mapper namespace="com.chaoku.modules.app.dao.UserDao">

	<!-- 可根据自己的需求，是否要使用 -->
    <resultMap type="com.chaoku.modules.app.entity.UserEntity" id="userMap">
        <result property="id" column="id"/>
        <result property="username" column="username"/>
        <result property="mobile" column="mobile"/>
        <result property="password" column="password"/>
        <result property="petCurrency" column="pet_currency"/>
        <result property="diamond" column="diamond"/>
        <result property="foodBread" column="food_bread"/>
        <result property="showerSoap" column="shower_soap"/>
        <result property="nickName" column="nick_name"/>
        <result property="gender" column="gender"/>
        <result property="language" column="language"/>
        <result property="city" column="city"/>
        <result property="province" column="province"/>
        <result property="country" column="country"/>
        <result property="avatarUrl" column="avatar_url"/>
        <result property="unionId" column="union_id"/>
        <result property="timestamp" column="timestamp"/>
        <result property="appid" column="appid"/>
        <result property="version" column="version"/>
        <result property="creator" column="creator"/>
        <result property="createDate" column="create_date"/>
        <result property="updater" column="updater"/>
        <result property="updateDate" column="update_date"/>
        <result property="delFlag" column="del_flag"/>
    </resultMap>


</mapper>